[
  { "size": "175/70R13", "width_mm": 175, "aspect": 70, "rim_in": 13, "common_name": "Küçük ekonomi", "weight_kg": 6.5 },
  { "size": "185/65R14", "width_mm": 185, "aspect": 65, "rim_in": 14, "common_name": "Standart kompakt", "weight_kg": 7.2 },
  { "size": "185/60R14", "width_mm": 185, "aspect": 60, "rim_in": 14, "common_name": "Kompakt performans", "weight_kg": 7.0 },
  { "size": "195/65R15", "width_mm": 195, "aspect": 65, "rim_in": 15, "common_name": "Standart orta sınıf", "weight_kg": 8.0 },
  { "size": "195/55R15", "width_mm": 195, "aspect": 55, "rim_in": 15, "common_name": "GTI style", "weight_kg": 7.8 },
  { "size": "195/50R15", "width_mm": 195, "aspect": 50, "rim_in": 15, "common_name": "Sport kompakt", "weight_kg": 7.5 },
  { "size": "205/55R16", "width_mm": 205, "aspect": 55, "rim_in": 16, "common_name": "Golf standart", "weight_kg": 8.5 },
  { "size": "205/50R16", "width_mm": 205, "aspect": 50, "rim_in": 16, "common_name": "Sport sedan", "weight_kg": 8.3 },
  { "size": "205/45R17", "width_mm": 205, "aspect": 45, "rim_in": 17, "common_name": "Spor kompakt 17\"", "weight_kg": 8.8 },
  { "size": "215/45R17", "width_mm": 215, "aspect": 45, "rim_in": 17, "common_name": "Golf R / Focus ST", "weight_kg": 9.1 },
  { "size": "215/40R17", "width_mm": 215, "aspect": 40, "rim_in": 17, "common_name": "Düşük profil sport", "weight_kg": 8.9 },
  { "size": "225/45R17", "width_mm": 225, "aspect": 45, "rim_in": 17, "common_name": "BMW 3-Serisi standart", "weight_kg": 9.5 },
  { "size": "225/40R18", "width_mm": 225, "aspect": 40, "rim_in": 18, "common_name": "Sport 18\" standard", "weight_kg": 9.8 },
  { "size": "235/40R18", "width_mm": 235, "aspect": 40, "rim_in": 18, "common_name": "BMW M serisi ön", "weight_kg": 10.2 },
  { "size": "245/40R18", "width_mm": 245, "aspect": 40, "rim_in": 18, "common_name": "BMW M3 arka / Porsche ön", "weight_kg": 10.6 },
  { "size": "255/35R18", "width_mm": 255, "aspect": 35, "rim_in": 18, "common_name": "Düşük profil geniş 18\"", "weight_kg": 10.5 },
  { "size": "255/40R18", "width_mm": 255, "aspect": 40, "rim_in": 18, "common_name": "Spor arka / Evo X", "weight_kg": 10.9 },
  { "size": "265/35R18", "width_mm": 265, "aspect": 35, "rim_in": 18, "common_name": "Geniş sport 18\"", "weight_kg": 11.0 },
  { "size": "275/35R18", "width_mm": 275, "aspect": 35, "rim_in": 18, "common_name": "GTR R35 arka / Geniş arka", "weight_kg": 11.5 },
  { "size": "285/35R18", "width_mm": 285, "aspect": 35, "rim_in": 18, "common_name": "Süper spor arka 18\"", "weight_kg": 12.0 },
  { "size": "225/35R19", "width_mm": 225, "aspect": 35, "rim_in": 19, "common_name": "Sport 19\" ön", "weight_kg": 10.0 },
  { "size": "235/35R19", "width_mm": 235, "aspect": 35, "rim_in": 19, "common_name": "Sport sedan 19\"", "weight_kg": 10.4 },
  { "size": "245/35R19", "width_mm": 245, "aspect": 35, "rim_in": 19, "common_name": "BMW M 19\" ön", "weight_kg": 10.8 },
  { "size": "255/35R19", "width_mm": 255, "aspect": 35, "rim_in": 19, "common_name": "Geniş ön 19\"", "weight_kg": 11.1 },
  { "size": "265/35R19", "width_mm": 265, "aspect": 35, "rim_in": 19, "common_name": "GTR arka / Supersport", "weight_kg": 11.6 },
  { "size": "275/30R19", "width_mm": 275, "aspect": 30, "rim_in": 19, "common_name": "Ferrari / Lamborghini style", "weight_kg": 11.3 },
  { "size": "285/30R19", "width_mm": 285, "aspect": 30, "rim_in": 19, "common_name": "Süper spor arka 19\"", "weight_kg": 11.8 },
  { "size": "295/30R19", "width_mm": 295, "aspect": 30, "rim_in": 19, "common_name": "Geniş arka süper spor", "weight_kg": 12.3 },
  { "size": "305/30R19", "width_mm": 305, "aspect": 30, "rim_in": 19, "common_name": "Gt3 arka / Ekstra geniş", "weight_kg": 12.8 },
  { "size": "245/40R19", "width_mm": 245, "aspect": 40, "rim_in": 19, "common_name": "SUV spor 19\"", "weight_kg": 11.4 },
  { "size": "255/40R19", "width_mm": 255, "aspect": 40, "rim_in": 19, "common_name": "M5 / RS6 arka", "weight_kg": 11.8 },
  { "size": "275/40R19", "width_mm": 275, "aspect": 40, "rim_in": 19, "common_name": "GTR R35 ön / SUV Geniş", "weight_kg": 12.2 },
  { "size": "225/30R20", "width_mm": 225, "aspect": 30, "rim_in": 20, "common_name": "Show car ön 20\"", "weight_kg": 10.5 },
  { "size": "245/35R20", "width_mm": 245, "aspect": 35, "rim_in": 20, "common_name": "Sport 20\" ön", "weight_kg": 11.2 },
  { "size": "255/35R20", "width_mm": 255, "aspect": 35, "rim_in": 20, "common_name": "Sport 20\"", "weight_kg": 11.6 },
  { "size": "265/35R20", "width_mm": 265, "aspect": 35, "rim_in": 20, "common_name": "SUV Spor arka 20\"", "weight_kg": 12.0 },
  { "size": "275/30R20", "width_mm": 275, "aspect": 30, "rim_in": 20, "common_name": "Süper spor 20\"", "weight_kg": 11.8 },
  { "size": "285/30R20", "width_mm": 285, "aspect": 30, "rim_in": 20, "common_name": "Porsche Turbo S arka", "weight_kg": 12.3 },
  { "size": "305/25R20", "width_mm": 305, "aspect": 25, "rim_in": 20, "common_name": "Drag slick / Ekstra geniş", "weight_kg": 12.1 },
  { "size": "315/25R20", "width_mm": 315, "aspect": 25, "rim_in": 20, "common_name": "Drag yarışı arka", "weight_kg": 12.5 },
  { "size": "325/25R20", "width_mm": 325, "aspect": 25, "rim_in": 20, "common_name": "Full drag arka 20\"", "weight_kg": 13.0 },
  { "size": "235/35R18", "width_mm": 235, "aspect": 35, "rim_in": 18, "common_name": "Düşük profil 18\"", "weight_kg": 10.0 },
  { "size": "295/35R18", "width_mm": 295, "aspect": 35, "rim_in": 18, "common_name": "Muscle car arka", "weight_kg": 12.5 },
  { "size": "315/30R18", "width_mm": 315, "aspect": 30, "rim_in": 18, "common_name": "Drag semi-slick 18\"", "weight_kg": 13.2 },
  { "size": "335/30R18", "width_mm": 335, "aspect": 30, "rim_in": 18, "common_name": "Pro drag 18\"", "weight_kg": 14.0 },
  { "size": "195/60R15", "width_mm": 195, "aspect": 60, "rim_in": 15, "common_name": "Eski Honda Civic style", "weight_kg": 7.9 },
  { "size": "215/55R16", "width_mm": 215, "aspect": 55, "rim_in": 16, "common_name": "Sedan orta sınıf", "weight_kg": 9.0 },
  { "size": "225/55R17", "width_mm": 225, "aspect": 55, "rim_in": 17, "common_name": "Crossover / SUV standart", "weight_kg": 10.5 },
  { "size": "235/55R17", "width_mm": 235, "aspect": 55, "rim_in": 17, "common_name": "SUV standart", "weight_kg": 11.0 },
  { "size": "245/45R18", "width_mm": 245, "aspect": 45, "rim_in": 18, "common_name": "Spor SUV", "weight_kg": 11.5 }
]
